reasy.py
version.py
collector/__init__.py
collector/collector.py
config/__init__.py
config/constants.py
config/yaml_config.py
m3u8_dl/__init__.py
m3u8_dl/aria2.py
m3u8_dl/downloader.py
m3u8_dl/parser.py
m3u8_dl/session.py
reasy-0.0.9.dist-info/METADATA
reasy-0.0.9.dist-info/WHEEL
reasy-0.0.9.dist-info/entry_points.txt
reasy-0.0.9.dist-info/top_level.txt
reasy-0.0.9.dist-info/RECORD
