Metadata-Version: 2.1
Name: reasy
Version: 0.0.9
Summary: A tool for quick downloading videos from BT7086
Home-page: UNKNOWN
Author: dekofejld
Author-email: dekofejld@gmail.com
License: MIT
Platform: UNKNOWN
Classifier: License :: OSI Approved :: MIT License
Classifier: Programming Language :: Python :: 3
Classifier: Programming Language :: Python :: 3.7
Requires-Dist: m3u8
Requires-Dist: aria2p
Requires-Dist: requests
Requires-Dist: click
Requires-Dist: pyyaml
